screenpy_playwright/__init__.py
screenpy_playwright/__version__.py
screenpy_playwright/abilities/__init__.py
screenpy_playwright/abilities/browse_the_web_synchronously.py
screenpy_playwright/actions/__init__.py
screenpy_playwright/actions/click.py
screenpy_playwright/actions/enter.py
screenpy_playwright/actions/open.py
screenpy_playwright/actions/refresh_the_page.py
screenpy_playwright/actions/save_console_log.py
screenpy_playwright/actions/save_screenshot.py
screenpy_playwright/actions/scroll.py
screenpy_playwright/actions/select.py
screenpy_playwright/exceptions.py
screenpy_playwright/protocols.py
screenpy_playwright/py.typed
screenpy_playwright/questions/__init__.py
screenpy_playwright/questions/attribute.py
screenpy_playwright/questions/browser_url.py
screenpy_playwright/questions/element.py
screenpy_playwright/questions/number.py
screenpy_playwright/questions/text.py
screenpy_playwright/resolutions/__init__.py
screenpy_playwright/resolutions/custom_matchers/__init__.py
screenpy_playwright/resolutions/custom_matchers/is_present_element.py
screenpy_playwright/resolutions/custom_matchers/is_visible_element.py
screenpy_playwright/resolutions/is_present.py
screenpy_playwright/resolutions/is_visible.py
screenpy_playwright/target.py
screenpy_playwright/target.pyi
screenpy_playwright-0.0.7.dist-info/LICENSE
screenpy_playwright-0.0.7.dist-info/METADATA
screenpy_playwright-0.0.7.dist-info/WHEEL
screenpy_playwright-0.0.7.dist-info/RECORD
