Metadata-Version: 2.1
Name: screenpy_playwright
Version: 0.0.7
Summary: ScreenPy extension to enable interacting with Playwright.
Home-page: https://github.com/ScreenPyHQ/screenpy_playwright
License: MIT
Author: Perry Goy
Author-email: perry.goy@gmail.com
Maintainer: Marcel Wilson
Requires-Python: >=3.8,<4.0
Classifier: Development Status :: 5 - Production/Stable
Classifier: Intended Audience :: Developers
Classifier: License :: OSI Approved :: MIT License
Classifier: Natural Language :: English
Classifier: Operating System :: OS Independent
Classifier: Programming Language :: Python :: 3
Classifier: Programming Language :: Python :: 3.8
Classifier: Programming Language :: Python :: 3.9
Classifier: Programming Language :: Python :: 3.10
Classifier: Programming Language :: Python :: 3.11
Classifier: Programming Language :: Python :: 3.12
Classifier: Programming Language :: Python :: 3 :: Only
Classifier: Topic :: Software Development :: Quality Assurance
Classifier: Topic :: Software Development :: Testing
Classifier: Topic :: Software Development :: Testing :: BDD
Provides-Extra: dev
Provides-Extra: docs
Provides-Extra: test
Requires-Dist: black ; extra == "dev"
Requires-Dist: coverage ; extra == "dev" or extra == "test"
Requires-Dist: cruft ; extra == "dev"
Requires-Dist: importlib_metadata ; python_version >= "3.8.dev0" and python_version < "3.9.dev0"
Requires-Dist: mypy ; extra == "dev"
Requires-Dist: playwright (>=1.39.0)
Requires-Dist: pre-commit ; extra == "dev"
Requires-Dist: pytest ; extra == "dev" or extra == "test"
Requires-Dist: pytest-mock ; extra == "dev" or extra == "test"
Requires-Dist: ruff (>=0.2.0) ; extra == "dev"
Requires-Dist: screenpy (>=4.0.2)
Requires-Dist: sphinx ; extra == "dev" or extra == "docs"
Requires-Dist: sphinx-rtd-theme ; extra == "dev" or extra == "docs"
Requires-Dist: tox ; extra == "dev"
Project-URL: Documentation, https://screenpy-playwright-docs.readthedocs.io
Project-URL: Repository, https://github.com/ScreenPyHQ/screenpy_playwright
